<?xml version="1.0" encoding="utf-8"?>
<search>
  
  
  
  <entry>
    <title>Hello World</title>
    <link href="/2023/01/01/hello-world/"/>
    <url>/2023/01/01/hello-world/</url>
    
    <content type="html"><![CDATA[<h1 id="2023元旦快乐"><a href="#2023元旦快乐" class="headerlink" title="2023元旦快乐"></a>2023元旦快乐</h1>]]></content>
    
    
    <categories>
      
      <category>Diary</category>
      
    </categories>
    
    
    <tags>
      
      <tag>PS3</tag>
      
    </tags>
    
  </entry>
  
  
  
  
</search>
